MANIFEST.in
README
setup.py
ML/__init__.py
ML/client.py
ML/errors.py
ML/log.py
ML/mime_type.py
ML/object_.py
ML/operation.py
ML/query.py
ML/relation.py
ML/server.py
ML/utils.py
maxleap_sdk.egg-info/PKG-INFO
maxleap_sdk.egg-info/SOURCES.txt
maxleap_sdk.egg-info/dependency_links.txt
maxleap_sdk.egg-info/requires.txt
maxleap_sdk.egg-info/top_level.txt