Metadata-Version: 1.1
Name: maxleap-sdk
Version: 0.2.0
Summary: MaxLeap Python SDK
Home-page: https://leap.as/
Author: czhou
Author-email: czhou@ilegendsoft.com
License: LGPL
Keywords: MaxLeap SDK
Platform: UNKNOWN
Classifier: Development Status :: 4 - Beta
Classifier: Intended Audience :: Developers
Classifier: Programming Language :: Python :: 2
Classifier: Programming Language :: Python :: 2.6
Classifier: Programming Language :: Python :: 2.7
